{
  "data": {
    "article": {},
    "attachments": {},
    "author_id": "2057552254463291393",
    "conversation_id": "2068679577677775152",
    "created_at": "2026-06-21T14:24:29.000Z",
    "edit_controls": {
      "editable_until": "2026-06-21T15:24:29.000Z",
      "edits_remaining": 5,
      "is_edit_eligible": false
    },
    "edit_history_tweet_ids": [
      "2068701594514837607"
    ],
    "entities": {
      "mentions": [
        {
          "end": 15,
          "id": "1426576940450914311",
          "start": 0,
          "username": "jitiantiantian"
        }
      ]
    },
    "geo": {},
    "id": "2068701594514837607",
    "in_reply_to_user_id": "1426576940450914311",
    "lang": "zh",
    "note_tweet": {
      "entities": {}
    },
    "possibly_sensitive": false,
    "public_metrics": {
      "bookmark_count": 0,
      "impression_count": 0,
      "like_count": 0,
      "quote_count": 0,
      "reply_count": 0,
      "retweet_count": 0
    },
    "referenced_tweets": [
      {
        "id": "2068697071188914635",
        "type": "replied_to"
      }
    ],
    "reply_settings": "everyone",
    "text": "@jitiantiantian 嘿嘿给你吃！🤤🤤❤"
  },
  "includes": {
    "tweets": [
      {
        "article": {},
        "attachments": {},
        "author_id": "2057552254463291393",
        "conversation_id": "2068679577677775152",
        "created_at": "2026-06-21T14:24:29.000Z",
        "edit_controls": {
          "editable_until": "2026-06-21T15:24:29.000Z",
          "edits_remaining": 5,
          "is_edit_eligible": false
        },
        "edit_history_tweet_ids": [
          "2068701594514837607"
        ],
        "entities": {
          "mentions": [
            {
              "end": 15,
              "id": "1426576940450914311",
              "start": 0,
              "username": "jitiantiantian"
            }
          ]
        },
        "geo": {},
        "id": "2068701594514837607",
        "in_reply_to_user_id": "1426576940450914311",
        "lang": "zh",
        "note_tweet": {
          "entities": {}
        },
        "possibly_sensitive": false,
        "public_metrics": {
          "bookmark_count": 0,
          "impression_count": 0,
          "like_count": 0,
          "quote_count": 0,
          "reply_count": 0,
          "retweet_count": 0
        },
        "referenced_tweets": [
          {
            "id": "2068697071188914635",
            "type": "replied_to"
          }
        ],
        "reply_settings": "everyone",
        "text": "@jitiantiantian 嘿嘿给你吃！🤤🤤❤"
      },
      {
        "article": {},
        "attachments": {},
        "author_id": "1426576940450914311",
        "conversation_id": "2068679577677775152",
        "created_at": "2026-06-21T14:06:30.000Z",
        "edit_controls": {
          "editable_until": "2026-06-21T15:06:30.000Z",
          "edits_remaining": 5,
          "is_edit_eligible": false
        },
        "edit_history_tweet_ids": [
          "2068697071188914635"
        ],
        "entities": {
          "mentions": [
            {
              "end": 9,
              "id": "2057552254463291393",
              "start": 0,
              "username": "6De_dian"
            }
          ]
        },
        "geo": {},
        "id": "2068697071188914635",
        "in_reply_to_user_id": "2057552254463291393",
        "lang": "zh",
        "note_tweet": {
          "entities": {}
        },
        "possibly_sensitive": false,
        "public_metrics": {
          "bookmark_count": 0,
          "impression_count": 6,
          "like_count": 1,
          "quote_count": 0,
          "reply_count": 1,
          "retweet_count": 0
        },
        "referenced_tweets": [
          {
            "id": "2068679577677775152",
            "type": "replied_to"
          }
        ],
        "reply_settings": "everyone",
        "text": "@6De_dian 全塞我嘴里"
      }
    ],
    "users": [
      {
        "created_at": "2026-05-21T20:03:58.000Z",
        "description": "可以叫我6点。\n我稀饭这个女孩呀。🤤❤@Korewoizontoyo\n｜双相｜ODer｜oc｜同人｜绝望De画手｜负能｜\n纯粹个人号发什么随心情\n正在学习药理中…\n\n可以私信我呀 很喜欢交朋友",
        "entities": {
          "description": {
            "mentions": [
              {
                "end": 34,
                "start": 19,
                "username": "Korewoizontoyo"
              }
            ]
          }
        },
        "id": "2057552254463291393",
        "name": "绝望_6De点",
        "pinned_tweet_id": "2059538750347128962",
        "profile_image_url": "https://pbs.twimg.com/profile_images/2057682303162187776/5rIQPIYV_normal.jpg",
        "protected": false,
        "public_metrics": {
          "followers_count": 125,
          "following_count": 205,
          "like_count": 3026,
          "listed_count": 0,
          "media_count": 26,
          "tweet_count": 407
        },
        "url": "",
        "username": "6De_dian",
        "verified": false
      },
      {
        "created_at": "2021-08-14T16:15:25.000Z",
        "description": "日记本｜自伤｜od",
        "id": "1426576940450914311",
        "name": "ちてんすず",
        "profile_image_url": "https://pbs.twimg.com/profile_images/2065515886019264512/2sq-zEc4_normal.jpg",
        "protected": false,
        "public_metrics": {
          "followers_count": 34,
          "following_count": 90,
          "like_count": 920,
          "listed_count": 0,
          "media_count": 15,
          "tweet_count": 244
        },
        "url": "",
        "username": "jitiantiantian",
        "verified": false
      }
    ]
  }
}