{
  "data": {
    "article": {},
    "attachments": {},
    "author_id": "2057552254463291393",
    "conversation_id": "2076090742624452914",
    "created_at": "2026-07-12T03:42:34.000Z",
    "edit_controls": {
      "editable_until": "2026-07-12T04:42:34.000Z",
      "edits_remaining": 5,
      "is_edit_eligible": false
    },
    "edit_history_tweet_ids": [
      "2076150195536924956"
    ],
    "entities": {
      "mentions": [
        {
          "end": 7,
          "id": "2056401954537136128",
          "start": 0,
          "username": "9WAY02"
        }
      ]
    },
    "geo": {},
    "id": "2076150195536924956",
    "in_reply_to_user_id": "2056401954537136128",
    "lang": "zh",
    "note_tweet": {
      "entities": {}
    },
    "possibly_sensitive": false,
    "public_metrics": {
      "bookmark_count": 0,
      "impression_count": 0,
      "like_count": 0,
      "quote_count": 0,
      "reply_count": 0,
      "retweet_count": 0
    },
    "referenced_tweets": [
      {
        "id": "2076138569316651099",
        "type": "replied_to"
      }
    ],
    "reply_settings": "everyone",
    "text": "@9WAY02 ohno。。不要医院，，要做好梦啊啊———"
  },
  "includes": {
    "tweets": [
      {
        "article": {},
        "attachments": {},
        "author_id": "2057552254463291393",
        "conversation_id": "2076090742624452914",
        "created_at": "2026-07-12T03:42:34.000Z",
        "edit_controls": {
          "editable_until": "2026-07-12T04:42:34.000Z",
          "edits_remaining": 5,
          "is_edit_eligible": false
        },
        "edit_history_tweet_ids": [
          "2076150195536924956"
        ],
        "entities": {
          "mentions": [
            {
              "end": 7,
              "id": "2056401954537136128",
              "start": 0,
              "username": "9WAY02"
            }
          ]
        },
        "geo": {},
        "id": "2076150195536924956",
        "in_reply_to_user_id": "2056401954537136128",
        "lang": "zh",
        "note_tweet": {
          "entities": {}
        },
        "possibly_sensitive": false,
        "public_metrics": {
          "bookmark_count": 0,
          "impression_count": 0,
          "like_count": 0,
          "quote_count": 0,
          "reply_count": 0,
          "retweet_count": 0
        },
        "referenced_tweets": [
          {
            "id": "2076138569316651099",
            "type": "replied_to"
          }
        ],
        "reply_settings": "everyone",
        "text": "@9WAY02 ohno。。不要医院，，要做好梦啊啊———"
      },
      {
        "article": {},
        "attachments": {},
        "author_id": "2056401954537136128",
        "conversation_id": "2076090742624452914",
        "created_at": "2026-07-12T02:56:22.000Z",
        "edit_controls": {
          "editable_until": "2026-07-12T03:56:22.000Z",
          "edits_remaining": 5,
          "is_edit_eligible": false
        },
        "edit_history_tweet_ids": [
          "2076138569316651099"
        ],
        "entities": {
          "mentions": [
            {
              "end": 9,
              "id": "2057552254463291393",
              "start": 0,
              "username": "6De_dian"
            }
          ]
        },
        "geo": {},
        "id": "2076138569316651099",
        "in_reply_to_user_id": "2057552254463291393",
        "lang": "zh",
        "note_tweet": {
          "entities": {}
        },
        "possibly_sensitive": false,
        "public_metrics": {
          "bookmark_count": 0,
          "impression_count": 5,
          "like_count": 1,
          "quote_count": 0,
          "reply_count": 1,
          "retweet_count": 0
        },
        "referenced_tweets": [
          {
            "id": "2076130858168184848",
            "type": "replied_to"
          }
        ],
        "reply_settings": "everyone",
        "text": "@6De_dian 这个好像没有哎，可能唯一的怪事是做了个噩梦？我又梦到自己被强制带去医院了"
      }
    ],
    "users": [
      {
        "created_at": "2026-05-21T20:03:58.000Z",
        "description": "可以叫我6点。\n\n让我明天 将一切重新来 该有多好？\n我一定更不负责任的生活 早知道。\n\n我稀饭这个女孩呀。🤤❤@Korewoizontoyo\n｜双相｜ODer｜oc｜同人｜绝望De画手｜负能｜\n纯粹个人号发什么随心情\n查属性回fo回私信\n药理学爱好，正在学习中…\n会尽力回答您的问题(´∀`)/\n\n可以私信我哦",
        "entities": {
          "description": {
            "mentions": [
              {
                "end": 71,
                "start": 56,
                "username": "Korewoizontoyo"
              }
            ]
          }
        },
        "id": "2057552254463291393",
        "location": "逝去",
        "name": "绝望_6De点",
        "pinned_tweet_id": "2071211057796776389",
        "profile_image_url": "https://pbs.twimg.com/profile_images/2071258839513526272/vtOebiN9_normal.jpg",
        "protected": false,
        "public_metrics": {
          "followers_count": 358,
          "following_count": 403,
          "like_count": 9226,
          "listed_count": 0,
          "media_count": 65,
          "tweet_count": 1606
        },
        "url": "",
        "username": "6De_dian",
        "verified": false
      },
      {
        "created_at": "2026-05-18T15:50:50.000Z",
        "description": "ISFP/2011/初二/女/不是黄推不聊骚纯绿/查成分互fo/上推只为发颠",
        "id": "2056401954537136128",
        "location": "🚪52，纯绿不线下。支持微信和口令还有usdt。",
        "name": "Dennis Nilsen",
        "pinned_tweet_id": "2058180141281603668",
        "profile_image_url": "https://pbs.twimg.com/profile_images/2057785546278371328/PX-Hx5Dq_normal.jpg",
        "protected": false,
        "public_metrics": {
          "followers_count": 132,
          "following_count": 186,
          "like_count": 1460,
          "listed_count": 0,
          "media_count": 46,
          "tweet_count": 915
        },
        "url": "",
        "username": "9WAY02",
        "verified": false
      }
    ]
  }
}