{
  "data": {
    "article": {},
    "attachments": {},
    "author_id": "2057552254463291393",
    "conversation_id": "2073128089253532076",
    "created_at": "2026-07-04T13:45:47.000Z",
    "edit_controls": {
      "editable_until": "2026-07-04T14:45:47.000Z",
      "edits_remaining": 5,
      "is_edit_eligible": false
    },
    "edit_history_tweet_ids": [
      "2073402896079606153"
    ],
    "entities": {
      "mentions": [
        {
          "end": 11,
          "id": "1916113741328093187",
          "start": 0,
          "username": "0nemoresec"
        }
      ]
    },
    "geo": {},
    "id": "2073402896079606153",
    "in_reply_to_user_id": "1916113741328093187",
    "lang": "zh",
    "note_tweet": {
      "entities": {}
    },
    "possibly_sensitive": false,
    "public_metrics": {
      "bookmark_count": 0,
      "impression_count": 0,
      "like_count": 0,
      "quote_count": 0,
      "reply_count": 0,
      "retweet_count": 0
    },
    "referenced_tweets": [
      {
        "id": "2073184079298879957",
        "type": "replied_to"
      }
    ],
    "reply_settings": "everyone",
    "text": "@0nemoresec 肺你不能输啊！！！🔥🔥🔥"
  },
  "includes": {
    "tweets": [
      {
        "article": {},
        "attachments": {},
        "author_id": "2057552254463291393",
        "conversation_id": "2073128089253532076",
        "created_at": "2026-07-04T13:45:47.000Z",
        "edit_controls": {
          "editable_until": "2026-07-04T14:45:47.000Z",
          "edits_remaining": 5,
          "is_edit_eligible": false
        },
        "edit_history_tweet_ids": [
          "2073402896079606153"
        ],
        "entities": {
          "mentions": [
            {
              "end": 11,
              "id": "1916113741328093187",
              "start": 0,
              "username": "0nemoresec"
            }
          ]
        },
        "geo": {},
        "id": "2073402896079606153",
        "in_reply_to_user_id": "1916113741328093187",
        "lang": "zh",
        "note_tweet": {
          "entities": {}
        },
        "possibly_sensitive": false,
        "public_metrics": {
          "bookmark_count": 0,
          "impression_count": 0,
          "like_count": 0,
          "quote_count": 0,
          "reply_count": 0,
          "retweet_count": 0
        },
        "referenced_tweets": [
          {
            "id": "2073184079298879957",
            "type": "replied_to"
          }
        ],
        "reply_settings": "everyone",
        "text": "@0nemoresec 肺你不能输啊！！！🔥🔥🔥"
      },
      {
        "article": {},
        "attachments": {},
        "author_id": "1916113741328093187",
        "conversation_id": "2073128089253532076",
        "created_at": "2026-07-03T23:16:17.000Z",
        "edit_controls": {
          "editable_until": "2026-07-04T00:16:17.000Z",
          "edits_remaining": 5,
          "is_edit_eligible": false
        },
        "edit_history_tweet_ids": [
          "2073184079298879957"
        ],
        "entities": {
          "mentions": [
            {
              "end": 9,
              "id": "2057552254463291393",
              "start": 0,
              "username": "6De_dian"
            }
          ]
        },
        "geo": {},
        "id": "2073184079298879957",
        "in_reply_to_user_id": "2057552254463291393",
        "lang": "ja",
        "note_tweet": {
          "entities": {}
        },
        "possibly_sensitive": false,
        "public_metrics": {
          "bookmark_count": 0,
          "impression_count": 65,
          "like_count": 4,
          "quote_count": 0,
          "reply_count": 1,
          "retweet_count": 0
        },
        "referenced_tweets": [
          {
            "id": "2073128089253532076",
            "type": "replied_to"
          }
        ],
        "reply_settings": "everyone",
        "text": "@6De_dian 锻炼起来💪💪"
      }
    ],
    "users": [
      {
        "created_at": "2026-05-21T20:03:58.000Z",
        "description": "可以叫我6点。\n\n让我明天 将一切重新来 该有多好？\n我一定更不负责任的生活 早知道。\n\n我稀饭这个女孩呀。🤤❤@Korewoizontoyo\n｜双相｜ODer｜oc｜同人｜绝望De画手｜负能｜\n纯粹个人号发什么随心情\n查属性回fo回私信\n药理学习中…\n\n可以私信我哦",
        "entities": {
          "description": {
            "mentions": [
              {
                "end": 71,
                "start": 56,
                "username": "Korewoizontoyo"
              }
            ]
          }
        },
        "id": "2057552254463291393",
        "location": "逝去",
        "name": "绝望_6De点",
        "pinned_tweet_id": "2071211057796776389",
        "profile_image_url": "https://pbs.twimg.com/profile_images/2071258839513526272/vtOebiN9_normal.jpg",
        "protected": false,
        "public_metrics": {
          "followers_count": 320,
          "following_count": 373,
          "like_count": 7755,
          "listed_count": 0,
          "media_count": 54,
          "tweet_count": 1281
        },
        "url": "",
        "username": "6De_dian",
        "verified": false
      },
      {
        "created_at": "2025-04-26T12:54:58.000Z",
        "description": "尸体在说话\n匿名信 https://t.co/dAFmIPsROM",
        "entities": {
          "description": {
            "urls": [
              {
                "display_url": "ngl.link/0nemoresec",
                "end": 33,
                "expanded_url": "https://ngl.link/0nemoresec",
                "start": 10,
                "url": "https://t.co/dAFmIPsROM"
              }
            ]
          }
        },
        "id": "1916113741328093187",
        "location": "空白",
        "name": "000",
        "pinned_tweet_id": "2068352892189438411",
        "profile_image_url": "https://pbs.twimg.com/profile_images/2063212015276232704/wKzUSuMr_normal.jpg",
        "protected": false,
        "public_metrics": {
          "followers_count": 160,
          "following_count": 160,
          "like_count": 3037,
          "listed_count": 0,
          "media_count": 51,
          "tweet_count": 1363
        },
        "url": "",
        "username": "0nemoresec",
        "verified": false
      }
    ]
  }
}